dipe/__init__.py
dipe/agent/__init__.py
dipe/constants/__init__.py
dipe/helpers/__init__.py
dipe/langchain/__init__.py
dipe/tools/__init__.py
dipe/tools/burn_and_close_account.py
dipe/tools/create_gibwork.py
dipe/tools/create_image.py
dipe/tools/create_meteora_dlmm_pool.py
dipe/tools/deploy_token.py
dipe/tools/fetch_price.py
dipe/tools/get_balance.py
dipe/tools/get_token_data.py
dipe/tools/get_tps.py
dipe/tools/launch_pumpfun_token.py
dipe/tools/lend.py
dipe/tools/request_faucet_funds.py
dipe/tools/stake_with_jup.py
dipe/tools/trade.py
dipe/tools/transfer.py
dipe/tools/use_moonshot.py
dipe/tools/use_pyth.py
dipe/tools/use_raydium.py
dipe/types/__init__.py
dipe/utils/__init__.py
dipe/utils/keypair.py
dipe/utils/meteora_dlmm/__init__.py
dipe/utils/meteora_dlmm/constants.py
dipe/utils/meteora_dlmm/helpers.py
dipe/utils/meteora_dlmm/idl.json
dipe/utils/meteora_dlmm/types.py
dipe/utils/meteora_dlmm/utils.py
dipe/utils/moonshot/__init__.py
dipe/utils/moonshot/constants.py
dipe/utils/moonshot/curve.py
dipe/utils/moonshot/idl.json
dipe/utils/moonshot/utils.py
dipe/utils/raydium/__init__.py
dipe/utils/raydium/constants.py
dipe/utils/raydium/layouts.py
dipe/utils/raydium/types.py
dipe/utils/raydium/utils.py
dipe/utils/send_tx.py
dipe/utils/toJSON.py
dipe-1.2.8.dist-info/LICENSE.md
dipe-1.2.8.dist-info/METADATA
dipe-1.2.8.dist-info/WHEEL
dipe-1.2.8.dist-info/RECORD
